advisor_cli/__init__.py
advisor_cli/cli.py
advisor_cli/cli_async.py
advisor_cli/cli_config.py
advisor_cli/cli_core.py
advisor_cli/cli_install.py
advisor_cli/cli_mcp.py
advisor_cli/cli_output.py
advisor_cli/cli_skill.py
advisor_cli/config.py
advisor_cli/core.py
advisor_cli/file_utils.py
advisor_cli/mcp_manager.py
advisor_cli/server.py
advisor_cli/setup_wizard.py
advisor_cli/skill_manager.py
advisor_cli/task_runner.py
advisor_cli/utils.py
advisor_cli/data/skills/advisor/SKILL.md
advisor_cli-0.2.11.dist-info/METADATA
advisor_cli-0.2.11.dist-info/WHEEL
advisor_cli-0.2.11.dist-info/entry_points.txt
advisor_cli-0.2.11.dist-info/licenses/LICENSE
advisor_cli-0.2.11.dist-info/RECORD
