Metadata-Version: 2.4
Name: advisor-cli
Version: 0.2.11
Summary: Get second opinions from alternative LLMs (Gemini, GPT, DeepSeek, Ollama)
Project-URL: Homepage, https://github.com/Andreymi/advisor-cli
Project-URL: Repository, https://github.com/Andreymi/advisor-cli
Project-URL: Documentation, https://github.com/Andreymi/advisor-cli#readme
Author: And#ocean
License-Expression: MIT
License-File: LICENSE
Keywords: ai,anthropic,claude,cli,gemini,llm,mcp,openai
Classifier: Development Status :: 4 - Beta
Classifier: Environment :: Console
Classifier: Intended Audience :: Developers
Classifier: License :: OSI Approved :: MIT License
Classifier: Programming Language :: Python :: 3.10
Classifier: Programming Language :: Python :: 3.11
Classifier: Programming Language :: Python :: 3.12
Classifier: Topic :: Software Development :: Libraries :: Python Modules
Requires-Python: >=3.10
Requires-Dist: litellm[caching]>=1.0.0
Requires-Dist: pydantic>=2.0.0
Requires-Dist: python-dotenv>=1.0.0
Requires-Dist: typer>=0.12.0
Provides-Extra: all
Requires-Dist: mcp>=1.0.0; extra == 'all'
Requires-Dist: questionary>=2.0.0; extra == 'all'
Requires-Dist: rich>=13.0.0; extra == 'all'
Provides-Extra: mcp
Requires-Dist: mcp>=1.0.0; extra == 'mcp'
Provides-Extra: wizard
Requires-Dist: questionary>=2.0.0; extra == 'wizard'
Requires-Dist: rich>=13.0.0; extra == 'wizard'
